server_status-1.1.1.dist-info/METADATA
server_status-1.1.1.dist-info/WHEEL
server_status-1.1.1.dist-info/entry_points.txt
server_status/__init__.py
server_status/__main__.py
server_status/api.py
server_status/cmd_parser.py
server_status/i18n.py
server_status-1.1.1.dist-info/RECORD
