Metadata-Version: 2.1
Name: server-status
Version: 1.1.1
Summary: Server status client
Author-Email: snowykami <snowykami@outlook.com>
License: MIT
Requires-Python: >=3.10
Requires-Dist: requests>=2.32.3
Requires-Dist: psutil>=6.0.0
Requires-Dist: arclet-alconna>=1.8.30
